{
  "upload_metadata": {
    "upload_date": "2025-08-18T22:30:19.343098",
    "crawler_type": "github",
    "filename": "github_20250819_051837_337413.json",
    "source": "github_crawler"
  },
  "artifact": {
    "id": "github_20250819_051837_337413",
    "url": "https://github.com/orhanveli/nestjs-saga-pattern-example",
    "title": "GitHub Repository: nestjs-saga-pattern-example",
    "description": "This is an example project for the usage of saga pattern (CQRS) with NestJS",
    "artifact_type": "code_repository",
    "source_category": "open_source",
    "content": "GitHub repository containing software architecture examples and patterns. Stars: 2, Language: TypeScript",
    "metadata": {
      "author": "orhanveli",
      "stars": 2,
      "forks": 0,
      "language": "TypeScript",
      "topics": [],
      "repository_type": "github",
      "last_updated": "2025-06-21T20:20:34Z",
      "has_issues": true,
      "has_wiki": true,
      "has_downloads": true,
      "owner": "orhanveli",
      "last_activity": "2025-06-21T20:20:34Z",
      "type_of_artifacts_found": {
        "diagrams": 0,
        "documents": 0,
        "code_files": 0,
        "config_files": 0,
        "architecture_files": 0,
        "documentation_files": 0
      },
      "artifact_details": {},
      "repository_stats": {
        "stars": 2,
        "forks": 0,
        "watchers": 2,
        "size_kb": 102,
        "language": "TypeScript",
        "topics": []
      }
    },
    "crawled_at": "2025-08-19T05:18:37.337419+00:00",
    "crawler_type": "github",
    "validation_status": "pending"
  }
}